django_pwnedpasswords_validator/__init__.py
django_pwnedpasswords_validator/metadata.py
django_pwnedpasswords_validator/validation.py
django_pwnedpasswords_validator-1.0.1.dist-info/METADATA
django_pwnedpasswords_validator-1.0.1.dist-info/RECORD
django_pwnedpasswords_validator-1.0.1.dist-info/WHEEL
django_pwnedpasswords_validator-1.0.1.dist-info/top_level.txt
