Metadata-Version: 2.1
Name: django-pwnedpasswords-validator
Version: 1.0.1
Summary: A Django app that validates user passwords against the Pwned Passwords v2 API.
Home-page: https://github.com/lionheart/django-pwnedpasswords-validator
Author: Dan Loewenherz
Author-email: dan@lionheartsw.com
License: Apache 2.0
Download-URL: https://github.com/lionheart/django-pwnedpasswords-validator/tarball/1.0.1
Keywords: passwords security
Platform: UNKNOWN
Classifier: Development Status :: 5 - Production/Stable
Classifier: Intended Audience :: Developers
Classifier: License :: OSI Approved :: Apache Software License
Classifier: Natural Language :: English
Classifier: Operating System :: OS Independent
Classifier: Operating System :: Unix
Classifier: Operating System :: MacOS :: MacOS X
Classifier: Programming Language :: Python :: 2.7
Classifier: Programming Language :: Python :: 3.5
Classifier: Programming Language :: Python :: 3.6
Classifier: Programming Language :: Python
Classifier: Topic :: Internet :: WWW/HTTP :: Dynamic Content :: CGI Tools/Libraries
Classifier: Topic :: Software Development :: Libraries
Classifier: Topic :: Software Development :: Libraries :: Python Modules
Classifier: Topic :: Utilities
Requires-Dist: pwnedpasswords
